chata/__init__.py
chata/cli.py
chata/core.py
chata/events.py
chata/pool.py
chata/stats/__init__.py
chata/stats/event_over_time.py
chata/stats/group.py
chata/stats/messages_per.py
chata/stats/people.py
chata/stats/people_tracker.py
chata/visualizations/__init__.py
chata/visualizations/average_messages_over_time_in_group.py
chata/visualizations/common_intervals.py
chata/visualizations/frequent_days.py
chata/visualizations/frequent_hours.py
chata/visualizations/group_names.py
chata/visualizations/leaderboard.py
chata/visualizations/least_active.py
chata/visualizations/messages_per_day.py
chata/visualizations/most_active.py
chata/visualizations/people_over_time.py
chata/visualizations/total_people.py
chata-0.2.1.dist-info/LICENSE
chata-0.2.1.dist-info/METADATA
chata-0.2.1.dist-info/WHEEL
chata-0.2.1.dist-info/entry_points.txt
chata-0.2.1.dist-info/top_level.txt
chata-0.2.1.dist-info/RECORD
