Metadata-Version: 2.1
Name: chata
Version: 0.2.1
Summary: A library for analysis and visualization of WhatsApp chats
Home-page: https://github.com/kmaork/chata
Author: Maor Kleinberger
Author-email: kmaork@gmail.com
License: UNKNOWN
Keywords: whatsapp library analysis visualization
Platform: UNKNOWN
Classifier: License :: OSI Approved :: MIT License
Classifier: Programming Language :: Python :: 3
Classifier: Programming Language :: Python :: 3 :: Only
Classifier: Programming Language :: Python :: 3.6
Classifier: Programming Language :: Python :: 3.7
Classifier: Programming Language :: Python :: 3.8
Classifier: Programming Language :: Python :: 3.9
Classifier: Topic :: Software Development :: Libraries :: Python Modules
Requires-Python: >=3.6
Requires-Dist: matplotlib
Requires-Dist: python-bidi
